{"timestamp":1743084727667,"data":[{"name":"Vivid Vulture","divine":13.1,"chaos":1600,"lowConfidence":true,"ratio":1},{"name":"Fenumal Plagued Arachnid","divine":10,"chaos":1220,"lowConfidence":true,"ratio":1},{"name":"Craicic Chimeral","divine":6.5,"chaos":793,"lowConfidence":true,"ratio":1},{"name":"Yellow Beasts","divine":3,"chaos":366,"lowConfidence":true,"ratio":1},{"name":"Wild Hellion Alpha","divine":1.69,"chaos":206,"lowConfidence":true,"ratio":1},{"name":"Vivid Watcher","divine":0.79,"chaos":96,"lowConfidence":true,"ratio":1},{"name":"Wild Bristle Matron","divine":0.58,"chaos":72,"lowConfidence":true,"ratio":1},{"name":"Wild Brambleback","divine":0.08,"chaos":10,"lowConfidence":true,"ratio":1},{"name":"Farric Tiger Alpha","divine":0.02,"chaos":3,"lowConfidence":true,"ratio":1}]}