{"timestamp":1696799584826,"data":[{"name":"Vivid Vulture","divine":9,"chaos":2533,"lowConfidence":true,"ratio":1},{"name":"Craicic Chimeral","divine":3.8,"chaos":1072,"lowConfidence":true,"ratio":1},{"name":"Vivid Watcher","divine":0.21,"chaos":58,"lowConfidence":true,"ratio":1},{"name":"Fenumal Plagued Arachnid","divine":0.07,"chaos":21,"lowConfidence":true,"ratio":1},{"name":"Wild Hellion Alpha","divine":0.05,"chaos":15,"lowConfidence":true,"ratio":1},{"name":"Wild Bristle Matron","divine":0.04,"chaos":12,"lowConfidence":true,"ratio":1},{"name":"Farric Wolf Alpha","divine":0.04,"chaos":10,"lowConfidence":true,"ratio":1},{"name":"Craicic Maw","divine":0.02,"chaos":7,"lowConfidence":true,"ratio":1},{"name":"Yellow Beasts","divine":0.01,"chaos":2,"lowConfidence":true,"ratio":1}]}