{"timestamp":1739643128715,"data":[{"name":"Vivid Vulture","divine":19,"chaos":2546,"lowConfidence":true,"ratio":1},{"name":"Craicic Chimeral","divine":8,"chaos":1056,"lowConfidence":true,"ratio":1},{"name":"Wild Hellion Alpha","divine":1.2,"chaos":158,"lowConfidence":true,"ratio":1},{"name":"Wild Brambleback","divine":1,"chaos":132,"lowConfidence":true,"ratio":1},{"name":"Wild Bristle Matron","divine":1,"chaos":132,"lowConfidence":true,"ratio":1},{"name":"Vivid Watcher","divine":0.2,"chaos":26,"lowConfidence":true,"ratio":1},{"name":"Yellow Beasts","divine":0.05,"chaos":7,"lowConfidence":true,"ratio":1}]}