{"timestamp":1655003121707,"data":[{"name":"Unrelenting 5 Way Set","exalt":7,"chaos":833,"lowConfidence":true},{"name":"Uber Elder Set","exalt":3,"chaos":357,"lowConfidence":true},{"name":"5 Way Set","exalt":1.8,"chaos":216,"lowConfidence":false},{"name":"Sirus Set","exalt":1.4,"chaos":168,"lowConfidence":true},{"name":"Maven's Writ","exalt":1.35,"chaos":162,"lowConfidence":true},{"name":"Elder Set","exalt":0.9,"chaos":109,"lowConfidence":false},{"name":"Shaper Set","exalt":0.5,"chaos":61,"lowConfidence":false}]}