{"timestamp":1653987900838,"data":[{"name":"Unrelenting 5 Way Set","exalt":7,"chaos":854,"lowConfidence":true},{"name":"Uber Elder Set","exalt":3,"chaos":369,"lowConfidence":true},{"name":"Maven's Writ","exalt":1.95,"chaos":238,"lowConfidence":true},{"name":"5 Way Set","exalt":1.8,"chaos":220,"lowConfidence":false},{"name":"Sirus Set","exalt":1.45,"chaos":180,"lowConfidence":true},{"name":"Elder Set","exalt":1,"chaos":123,"lowConfidence":false},{"name":"Shaper Set","exalt":0.5,"chaos":61,"lowConfidence":true}]}