{"timestamp":1654592714965,"data":[{"name":"Unrelenting 5 Way Set","exalt":7,"chaos":854,"lowConfidence":true},{"name":"Maven's Writ","exalt":1.8,"chaos":220,"lowConfidence":true},{"name":"5 Way Set","exalt":1.1,"chaos":134,"lowConfidence":false},{"name":"Elder Set","exalt":1,"chaos":122,"lowConfidence":false},{"name":"Shaper Set","exalt":0.5,"chaos":61,"lowConfidence":false},{"name":"Uber Elder Set","exalt":0.15,"chaos":18,"lowConfidence":true},{"name":"Sirus Set","exalt":0.06,"chaos":8,"lowConfidence":true}]}