{"timestamp":1693383185700,"data":[{"name":"Uber Elder Set","divine":2,"chaos":562,"lowConfidence":true,"ratio":1},{"name":"Maven's Writ","divine":1.1,"chaos":310,"lowConfidence":true,"ratio":1},{"name":"Elder Set","divine":0.42,"chaos":118,"lowConfidence":true,"ratio":1},{"name":"5 Way Set","divine":0.4,"chaos":112,"lowConfidence":true,"ratio":1},{"name":"Sirus Set","divine":0.4,"chaos":112,"lowConfidence":true,"ratio":1},{"name":"Shaper Set","divine":0.2,"chaos":56,"lowConfidence":true,"ratio":1}]}