{"timestamp":1710461614878,"data":[{"name":"Yellow Plants","divine":2.01,"chaos":550,"lowConfidence":true,"ratio":1},{"name":"Purple Plants","divine":0.81,"chaos":216,"lowConfidence":true,"ratio":1},{"name":"Blue Plants","divine":0.77,"chaos":210,"lowConfidence":true,"ratio":1},{"name":"Conqueror Map","divine":0.59,"chaos":157,"lowConfidence":true,"ratio":1},{"name":"Strongbox Enraged","divine":0.39,"chaos":104,"lowConfidence":true,"ratio":1},{"name":"8 Modifiers","divine":0.33,"chaos":90,"lowConfidence":true,"ratio":1},{"name":"Sacred Grove","divine":0.21,"chaos":58,"lowConfidence":true,"ratio":1},{"name":"Delirium Reward","divine":0.19,"chaos":53,"lowConfidence":true,"ratio":1},{"name":"Beyond","divine":0.19,"chaos":52,"lowConfidence":true,"ratio":1},{"name":"Mysterious Harbinger","divine":0.19,"chaos":50,"lowConfidence":true,"ratio":1},{"name":"Mirror of Delirium","divine":0.15,"chaos":40,"lowConfidence":true,"ratio":1},{"name":"Shaper Guardian","divine":0.11,"chaos":30,"lowConfidence":true,"ratio":1},{"name":"Gilded Scarab","divine":0.09,"chaos":23,"lowConfidence":true,"ratio":1},{"name":"Alva","divine":0.07,"chaos":20,"lowConfidence":true,"ratio":1},{"name":"Splinters Emblems Duplicate","divine":0.07,"chaos":18,"lowConfidence":true,"ratio":1},{"name":"Strongbox Corrupted","divine":0.05,"chaos":15,"lowConfidence":true,"ratio":1},{"name":"Elder Guardian","divine":0.05,"chaos":13,"lowConfidence":true,"ratio":1},{"name":"Polished Scarab","divine":0.04,"chaos":10,"lowConfidence":true,"ratio":1},{"name":"Unidentified Map","divine":0.04,"chaos":10,"lowConfidence":true,"ratio":1},{"name":"Abyss","divine":0.03,"chaos":9,"lowConfidence":true,"ratio":1},{"name":"Breach","divine":0.03,"chaos":8,"lowConfidence":true,"ratio":1},{"name":"Legion","divine":0.03,"chaos":8,"lowConfidence":true,"ratio":1},{"name":"Ritual Rerolling","divine":0.03,"chaos":8,"lowConfidence":true,"ratio":1},{"name":"Ritual Altars","divine":0.03,"chaos":7,"lowConfidence":true,"ratio":1},{"name":"Essence","divine":0.02,"chaos":6,"lowConfidence":true,"ratio":1}]}