{"timestamp":1746652318502,"data":[{"name":"Vivid Vulture","divine":28,"chaos":3472,"lowConfidence":true,"ratio":1},{"name":"Fenumal Plagued Arachnid","divine":10,"chaos":1240,"lowConfidence":true,"ratio":1},{"name":"Craicic Chimeral","divine":7,"chaos":868,"lowConfidence":true,"ratio":1},{"name":"Wild Hellion Alpha","divine":4,"chaos":496,"lowConfidence":true,"ratio":1},{"name":"Vivid Watcher","divine":1.5,"chaos":186,"lowConfidence":true,"ratio":1},{"name":"Yellow Beasts","divine":1.43,"chaos":174,"lowConfidence":true,"ratio":1},{"name":"Wild Bristle Matron","divine":1,"chaos":124,"lowConfidence":true,"ratio":1},{"name":"Wild Brambleback","divine":0.08,"chaos":11,"lowConfidence":true,"ratio":1}]}