{"timestamp":1656039942634,"data":[{"name":"Boss drop Conqueror Map","exalt":2,"chaos":244,"lowConfidence":true},{"name":"Harvests contain Blue Plants","exalt":1.5,"chaos":183,"lowConfidence":false},{"name":"Harvests contain Purple Plants","exalt":0.92,"chaos":109,"lowConfidence":false},{"name":"Attract Monsters from Beyond","exalt":0.87,"chaos":106,"lowConfidence":false},{"name":"Additional Monsters deal Chaos","exalt":0.85,"chaos":100,"lowConfidence":true},{"name":"Ritual Rerolling Favours No Cost","exalt":0.57,"chaos":70,"lowConfidence":false},{"name":"Unique Monsters drop Corrupted Items","exalt":0.59,"chaos":70,"lowConfidence":false},{"name":"Expedition Runic Monster Markers","exalt":0.56,"chaos":68,"lowConfidence":false},{"name":"Breaches belong to Chayula","exalt":0.37,"chaos":45,"lowConfidence":false},{"name":"Harvests contain Yellow Plants","exalt":0.38,"chaos":45,"lowConfidence":false},{"name":"Legion Splinters & Emblems Duplicate","exalt":0.33,"chaos":40,"lowConfidence":false},{"name":"Strongbox Enraged & Increased Quant","exalt":0.33,"chaos":40,"lowConfidence":false},{"name":"Syndicate Intelligence","exalt":0.33,"chaos":40,"lowConfidence":true},{"name":"Vaal Gifts of the Red Queen/Sacrificed","exalt":0.33,"chaos":39,"lowConfidence":true},{"name":"Areas contain Ritual Altars","exalt":0.29,"chaos":35,"lowConfidence":false},{"name":"Boss drop Shaper Guardian Map","exalt":0.26,"chaos":32,"lowConfidence":true},{"name":"Areas contain Alva","exalt":0.25,"chaos":30,"lowConfidence":false},{"name":"Possessed Monsters drop Gilded Scarab","exalt":0.25,"chaos":30,"lowConfidence":false},{"name":"Boss drop Elder Guardian Map","exalt":0.2,"chaos":24,"lowConfidence":false},{"name":"Areas contain Jun","exalt":0.19,"chaos":22,"lowConfidence":false},{"name":"Quality of Maps Applies to Rarity","exalt":0.17,"chaos":20,"lowConfidence":true},{"name":"Vaal Don't Apply Soul Gain Prevention","exalt":0.17,"chaos":20,"lowConfidence":true},{"name":"Harbingers drop Shards","exalt":0.16,"chaos":19,"lowConfidence":true},{"name":"Areas contain Tormented Heretic","exalt":0.13,"chaos":15,"lowConfidence":true},{"name":"Possessed Monsters drop Polished Scarab","exalt":0.13,"chaos":15,"lowConfidence":true},{"name":"20% Pack Size Unidentified Map","exalt":0.08,"chaos":10,"lowConfidence":true},{"name":"25% increased Magic Pack Size","exalt":0.08,"chaos":10,"lowConfidence":true},{"name":"Areas contain Einhar","exalt":0.08,"chaos":10,"lowConfidence":true},{"name":"Areas contain Gloom Shrine","exalt":0.08,"chaos":10,"lowConfidence":true},{"name":"Areas contain Heist Smuggler's Cache","exalt":0.08,"chaos":10,"lowConfidence":true},{"name":"Areas contain Hunted Traitors","exalt":0.08,"chaos":10,"lowConfidence":true},{"name":"Areas contain Legion","exalt":0.08,"chaos":10,"lowConfidence":true},{"name":"Breaches belong to Tul","exalt":0.08,"chaos":10,"lowConfidence":true},{"name":"2 additional Strongbox Corrupted & Rare","exalt":0.08,"chaos":9,"lowConfidence":true},{"name":"Areas contain Abyss","exalt":0.07,"chaos":9,"lowConfidence":true},{"name":"Areas contain Metamorph","exalt":0.07,"chaos":9,"lowConfidence":true},{"name":"Areas inhabited Rogue Exiles","exalt":0.08,"chaos":9,"lowConfidence":true},{"name":"Blight Oils Found 1 Tier Higher","exalt":0.07,"chaos":9,"lowConfidence":true},{"name":"Areas contain Breach","exalt":0.07,"chaos":8,"lowConfidence":true},{"name":"Heist Contracts have Implicit","exalt":0.07,"chaos":8,"lowConfidence":true},{"name":"Areas contain Harvest Sacred Grove","exalt":0.06,"chaos":7,"lowConfidence":true},{"name":"Players cannot take Reflected Damage","exalt":0.06,"chaos":7,"lowConfidence":true},{"name":"Areas contain Blight","exalt":0.05,"chaos":6,"lowConfidence":true},{"name":"Areas contain Essence","exalt":0.05,"chaos":6,"lowConfidence":true},{"name":"Breaches belong to Esh","exalt":0.05,"chaos":6,"lowConfidence":true},{"name":"Breaches belong to Xoph","exalt":0.05,"chaos":6,"lowConfidence":true},{"name":"Maps Corrupted with 8 Modifiers","exalt":0.04,"chaos":5,"lowConfidence":false},{"name":"Delirium Reward fill faster","exalt":0.03,"chaos":4,"lowConfidence":false},{"name":"Create Copy of Beasts","exalt":0.02,"chaos":2,"lowConfidence":true},{"name":"Mirror of Delirium","exalt":0.02,"chaos":2,"lowConfidence":true},{"name":"Breaches belong to Uul-Netol","exalt":0.01,"chaos":1,"lowConfidence":true},{"name":"Metamorph Catalysts Duplicate","exalt":0.01,"chaos":1,"lowConfidence":true}]}