{"timestamp":1644840225114,"data":[{"name":"T4 Aisling","exalt":8,"chaos":816,"lowConfidence":false},{"name":"T4 Hillock Armour 30%","exalt":8,"chaos":816,"lowConfidence":false},{"name":"T4 Hillock Flask 28%","exalt":5,"chaos":510,"lowConfidence":false},{"name":"T4 Hillock Weapon 30%","exalt":4,"chaos":408,"lowConfidence":true},{"name":"Leo Exalt Slam","exalt":2,"chaos":204,"lowConfidence":true},{"name":"T3/T2/T1 Vorici White","exalt":3,"chaos":309,"lowConfidence":true},{"name":"T4/T3 It That Fled Pure Breachstone","exalt":5,"chaos":510,"lowConfidence":true},{"name":"T4 Vorici 1-6 White","exalt":5.5,"chaos":566,"lowConfidence":false},{"name":"Locus of Corruption (Item)","exalt":2,"chaos":206,"lowConfidence":true}]}