{"timestamp":1658329409777,"data":[{"name":"Uber Elder Set","exalt":2,"chaos":352,"lowConfidence":false},{"name":"Unrelenting 5 Way Set","exalt":1.9,"chaos":341,"lowConfidence":true},{"name":"5 Way Set","exalt":1.32,"chaos":232,"lowConfidence":false},{"name":"Elder Set","exalt":0.5,"chaos":88,"lowConfidence":false},{"name":"Maven's Writ","exalt":0.5,"chaos":88,"lowConfidence":false},{"name":"Shaper Set","exalt":0.4,"chaos":70,"lowConfidence":false},{"name":"Sirus Set","exalt":0.32,"chaos":56,"lowConfidence":false}]}