{"timestamp":1649008945481,"data":[{"name":"Craicic Chimeral","exalt":1,"chaos":174,"lowConfidence":false},{"name":"Craicic Maw","exalt":0.17,"chaos":29,"lowConfidence":false},{"name":"Craicic Savage Crab","exalt":0.05,"chaos":8,"lowConfidence":true},{"name":"Saqawine Cobra","exalt":0.11,"chaos":20,"lowConfidence":true},{"name":"Farric Lynx Alpha","exalt":0.09,"chaos":16,"lowConfidence":false},{"name":"Farric Tiger Alpha","exalt":0.1,"chaos":18,"lowConfidence":false},{"name":"Farric Wolf Alpha","exalt":0.14,"chaos":25,"lowConfidence":false},{"name":"Fenumal Plagued Arachnid","exalt":0.35,"chaos":61,"lowConfidence":false}]}