{"timestamp":1667822507076,"data":[{"name":"Incandescent Invitation","divine":0.8,"chaos":121,"lowConfidence":true},{"name":"Screaming Invitation","divine":0.72,"chaos":110,"lowConfidence":true},{"name":"Writhing Invitation","divine":0.3,"chaos":44,"lowConfidence":true},{"name":"Polaric Invitation","divine":0.04,"chaos":6,"lowConfidence":true},{"name":"The Formed","divine":0.78,"chaos":118,"lowConfidence":true},{"name":"The Elderslayers","divine":0.47,"chaos":70,"lowConfidence":true},{"name":"The Twisted","divine":0.33,"chaos":50,"lowConfidence":true},{"name":"The Feared","divine":0.05,"chaos":7,"lowConfidence":true}]}