{"timestamp":1691478701541,"data":[{"name":"Uber Elder Set","divine":2,"chaos":384,"lowConfidence":true,"ratio":1},{"name":"Maven's Writ","divine":1.2,"chaos":230,"lowConfidence":true,"ratio":1},{"name":"5 Way Set","divine":0.46,"chaos":89,"lowConfidence":true,"ratio":1},{"name":"Sirus Set","divine":0.35,"chaos":67,"lowConfidence":false,"ratio":1},{"name":"Elder Set","divine":0.35,"chaos":66,"lowConfidence":true,"ratio":1},{"name":"Shaper Set","divine":0.34,"chaos":65,"lowConfidence":false,"ratio":1}]}