{"timestamp":1704291112093,"data":[{"name":"Uber Elder Set","divine":3.3,"chaos":716,"lowConfidence":false,"ratio":1},{"name":"Maven's Writ","divine":2.7,"chaos":586,"lowConfidence":false,"ratio":1},{"name":"Sirus Set","divine":1.45,"chaos":315,"lowConfidence":false,"ratio":1},{"name":"Unrelenting 5 Way Set","divine":1.21,"chaos":263,"lowConfidence":true,"ratio":1},{"name":"5 Way Set","divine":1,"chaos":217,"lowConfidence":false,"ratio":1},{"name":"Elder Set","divine":1,"chaos":217,"lowConfidence":false,"ratio":1},{"name":"Shaper Set","divine":0.5,"chaos":109,"lowConfidence":false,"ratio":1}]}