{"timestamp":1662476535459,"data":[{"name":"Vaal Temple","divine":0.06,"chaos":11,"lowConfidence":false},{"name":"Coves","divine":0.05,"chaos":8,"lowConfidence":true},{"name":"Beach","divine":0.04,"chaos":7,"lowConfidence":true},{"name":"Alleyways","divine":0.03,"chaos":6,"lowConfidence":true},{"name":"Maze","divine":0.03,"chaos":6,"lowConfidence":true},{"name":"Terrace","divine":0.03,"chaos":6,"lowConfidence":true},{"name":"Bog","divine":0.03,"chaos":5,"lowConfidence":true},{"name":"Mesa","divine":0.03,"chaos":5,"lowConfidence":false},{"name":"Promenade","divine":0.03,"chaos":5,"lowConfidence":true},{"name":"Strand","divine":0.03,"chaos":5,"lowConfidence":false},{"name":"Temple","divine":0.03,"chaos":5,"lowConfidence":true},{"name":"Thicket","divine":0.03,"chaos":5,"lowConfidence":true},{"name":"Underground Sea","divine":0.03,"chaos":5,"lowConfidence":true},{"name":"Villa","divine":0.03,"chaos":5,"lowConfidence":true},{"name":"Atoll","divine":0.02,"chaos":4,"lowConfidence":false},{"name":"Cemetery","divine":0.03,"chaos":4,"lowConfidence":true},{"name":"Chateau","divine":0.02,"chaos":4,"lowConfidence":true},{"name":"Crimson Temple","divine":0.02,"chaos":4,"lowConfidence":false},{"name":"Crimson Township","divine":0.02,"chaos":4,"lowConfidence":true},{"name":"Defiled Cathedral","divine":0.02,"chaos":4,"lowConfidence":false},{"name":"Dunes","divine":0.02,"chaos":4,"lowConfidence":false},{"name":"Forking River","divine":0.02,"chaos":4,"lowConfidence":true},{"name":"Grotto","divine":0.03,"chaos":4,"lowConfidence":true},{"name":"Mud Geyser","divine":0.02,"chaos":4,"lowConfidence":true},{"name":"Park","divine":0.02,"chaos":4,"lowConfidence":false},{"name":"Plateau","divine":0.02,"chaos":4,"lowConfidence":true},{"name":"Arcade","divine":0.02,"chaos":3,"lowConfidence":true},{"name":"Arid Lake","divine":0.02,"chaos":3,"lowConfidence":true},{"name":"Ashen Wood","divine":0.02,"chaos":3,"lowConfidence":true},{"name":"Cells","divine":0.02,"chaos":3,"lowConfidence":true},{"name":"Cursed Crypt","divine":0.02,"chaos":3,"lowConfidence":true},{"name":"Overgrown Ruin","divine":0.02,"chaos":3,"lowConfidence":true},{"name":"Ramparts","divine":0.02,"chaos":3,"lowConfidence":true},{"name":"Shore","divine":0.02,"chaos":3,"lowConfidence":true},{"name":"Sulphur Vents","divine":0.02,"chaos":3,"lowConfidence":true},{"name":"Arsenal","divine":0.01,"chaos":2,"lowConfidence":true},{"name":"Carcass","divine":0.01,"chaos":2,"lowConfidence":true},{"name":"Vault","divine":0.01,"chaos":2,"lowConfidence":true},{"name":"Waste Pool","divine":0.01,"chaos":2,"lowConfidence":true},{"name":"Lava Chamber","divine":0.01,"chaos":1,"lowConfidence":true},{"name":"Marshes","divine":0.01,"chaos":1,"lowConfidence":true},{"name":"Beachhead Maps","divine":1,"chaos":174,"lowConfidence":true},{"name":"Conqueror Maps","divine":0.16,"chaos":28,"lowConfidence":false},{"name":"Elder Maps","divine":0.11,"chaos":19,"lowConfidence":false},{"name":"Shaper Maps","divine":0.09,"chaos":16,"lowConfidence":false},{"name":"Blighted Maps","divine":0.08,"chaos":13,"lowConfidence":false}]}