{"timestamp":1650423771648,"data":[{"name":"Uber Elder Set","exalt":2.27,"chaos":363,"lowConfidence":false},{"name":"Unrelenting 5 Way Set","exalt":1.95,"chaos":318,"lowConfidence":true},{"name":"5 Way Set","exalt":1.3,"chaos":210,"lowConfidence":false},{"name":"Maven's Writ","exalt":0.67,"chaos":105,"lowConfidence":false},{"name":"Sirus Set","exalt":0.57,"chaos":90,"lowConfidence":true},{"name":"Elder Set","exalt":0.5,"chaos":79,"lowConfidence":false},{"name":"Shaper Set","exalt":0.33,"chaos":53,"lowConfidence":false}]}