{"timestamp":1671624134325,"data":[{"name":"Tower","divine":0.87,"chaos":174,"lowConfidence":true},{"name":"Phantasmagoria","divine":0.6,"chaos":120,"lowConfidence":true},{"name":"Museum","divine":0.22,"chaos":50,"lowConfidence":true},{"name":"Moon Temple","divine":0.17,"chaos":40,"lowConfidence":true},{"name":"Cursed Crypt","divine":0.14,"chaos":32,"lowConfidence":true},{"name":"Vaal Temple","divine":0.06,"chaos":13,"lowConfidence":false},{"name":"Atoll","divine":0.03,"chaos":8,"lowConfidence":true},{"name":"Canyon","divine":0.03,"chaos":8,"lowConfidence":true},{"name":"Coves","divine":0.03,"chaos":8,"lowConfidence":true},{"name":"Glacier","divine":0.04,"chaos":8,"lowConfidence":true},{"name":"Mausoleum","divine":0.02,"chaos":6,"lowConfidence":true},{"name":"Shore","divine":0.03,"chaos":6,"lowConfidence":true},{"name":"Silo","divine":0.03,"chaos":6,"lowConfidence":true},{"name":"City Square","divine":0.02,"chaos":5,"lowConfidence":false},{"name":"Colonnade","divine":0.02,"chaos":5,"lowConfidence":true},{"name":"Crimson Temple","divine":0.02,"chaos":5,"lowConfidence":false},{"name":"Crimson Township","divine":0.02,"chaos":5,"lowConfidence":true},{"name":"Defiled Cathedral","divine":0.02,"chaos":5,"lowConfidence":false},{"name":"Dunes","divine":0.02,"chaos":5,"lowConfidence":false},{"name":"Graveyard","divine":0.02,"chaos":5,"lowConfidence":false},{"name":"Mesa","divine":0.02,"chaos":5,"lowConfidence":false},{"name":"Necropolis","divine":0.03,"chaos":5,"lowConfidence":true},{"name":"Promenade","divine":0.02,"chaos":5,"lowConfidence":true},{"name":"Strand","divine":0.02,"chaos":5,"lowConfidence":false},{"name":"Temple","divine":0.02,"chaos":5,"lowConfidence":true},{"name":"Toxic Sewer","divine":0.02,"chaos":5,"lowConfidence":false},{"name":"Underground Sea","divine":0.02,"chaos":5,"lowConfidence":true},{"name":"Wasteland","divine":0.02,"chaos":5,"lowConfidence":true},{"name":"Alleyways","divine":0.02,"chaos":4,"lowConfidence":true},{"name":"Ashen Wood","divine":0.02,"chaos":4,"lowConfidence":true},{"name":"Burial Chambers","divine":0.02,"chaos":4,"lowConfidence":true},{"name":"Cemetery","divine":0.02,"chaos":4,"lowConfidence":true},{"name":"Cold River","divine":0.02,"chaos":4,"lowConfidence":true},{"name":"Dry Sea","divine":0.02,"chaos":4,"lowConfidence":true},{"name":"Foundry","divine":0.02,"chaos":4,"lowConfidence":true},{"name":"Infested Valley","divine":0.02,"chaos":4,"lowConfidence":true},{"name":"Lair","divine":0.02,"chaos":4,"lowConfidence":true},{"name":"Sunken City","divine":0.02,"chaos":4,"lowConfidence":true},{"name":"Ancient City","divine":0.01,"chaos":3,"lowConfidence":true},{"name":"Carcass","divine":0.01,"chaos":3,"lowConfidence":false},{"name":"Courthouse","divine":0.01,"chaos":3,"lowConfidence":true},{"name":"Forbidden Woods","divine":0.01,"chaos":3,"lowConfidence":true},{"name":"Ghetto","divine":0.01,"chaos":3,"lowConfidence":true},{"name":"Grotto","divine":0.01,"chaos":3,"lowConfidence":true},{"name":"Leyline","divine":0.01,"chaos":3,"lowConfidence":true},{"name":"Orchard","divine":0.01,"chaos":3,"lowConfidence":true},{"name":"Overgrown Ruin","divine":0.01,"chaos":3,"lowConfidence":true},{"name":"Overgrown Shrine","divine":0.01,"chaos":3,"lowConfidence":true},{"name":"Underground River","divine":0.01,"chaos":3,"lowConfidence":true},{"name":"Vault","divine":0.01,"chaos":2,"lowConfidence":true},{"name":"Conqueror Maps","divine":0.17,"chaos":38,"lowConfidence":false},{"name":"Elder Maps","divine":0.08,"chaos":18,"lowConfidence":false},{"name":"Shaper Maps","divine":0.08,"chaos":18,"lowConfidence":false},{"name":"Beachhead Maps","divine":0.08,"chaos":17,"lowConfidence":true},{"name":"Blighted Maps","divine":0.03,"chaos":8,"lowConfidence":false}]}