{"timestamp":1700363460405,"data":[{"name":"Incandescent Invitation","divine":1.32,"chaos":319,"lowConfidence":true,"ratio":1},{"name":"Screaming Invitation","divine":1.25,"chaos":301,"lowConfidence":false,"ratio":1},{"name":"Polaric Invitation","divine":0.05,"chaos":12,"lowConfidence":true,"ratio":1},{"name":"Writhing Invitation","divine":0.04,"chaos":10,"lowConfidence":true,"ratio":1},{"name":"The Elderslayers","divine":0.5,"chaos":121,"lowConfidence":true,"ratio":1},{"name":"The Formed","divine":0.5,"chaos":121,"lowConfidence":true,"ratio":1},{"name":"The Twisted","divine":0.5,"chaos":121,"lowConfidence":true,"ratio":1},{"name":"The Feared","divine":0.04,"chaos":10,"lowConfidence":true,"ratio":1},{"name":"The Forgotten","divine":0.04,"chaos":10,"lowConfidence":true,"ratio":1},{"name":"The Hidden","divine":0.03,"chaos":7,"lowConfidence":true,"ratio":1}]}