{"timestamp":1706541068887,"data":[{"name":"Screaming Invitation","divine":3.2,"chaos":531,"lowConfidence":false,"ratio":1},{"name":"Incandescent Invitation","divine":2.7,"chaos":455,"lowConfidence":false,"ratio":1},{"name":"Writhing Invitation","divine":0.23,"chaos":48,"lowConfidence":true,"ratio":1},{"name":"Polaric Invitation","divine":0.12,"chaos":20,"lowConfidence":true,"ratio":1},{"name":"The Elderslayers","divine":1.8,"chaos":301,"lowConfidence":false,"ratio":1},{"name":"The Formed","divine":1.5,"chaos":252,"lowConfidence":false,"ratio":1},{"name":"The Twisted","divine":1.11,"chaos":188,"lowConfidence":false,"ratio":1},{"name":"The Hidden","divine":0.18,"chaos":30,"lowConfidence":true,"ratio":1},{"name":"The Forgotten","divine":0.16,"chaos":27,"lowConfidence":true,"ratio":1},{"name":"The Feared","divine":0.11,"chaos":18,"lowConfidence":true,"ratio":1}]}