{"timestamp":1710483059959,"data":[{"name":"Incandescent Invitation","divine":2.29,"chaos":343,"lowConfidence":true,"ratio":1},{"name":"Screaming Invitation","divine":2.31,"chaos":341,"lowConfidence":false,"ratio":1},{"name":"The Elderslayers","divine":2.2,"chaos":323,"lowConfidence":true,"ratio":1},{"name":"The Twisted","divine":1.15,"chaos":170,"lowConfidence":true,"ratio":1},{"name":"The Formed","divine":1,"chaos":148,"lowConfidence":true,"ratio":1},{"name":"The Forgotten","divine":0.27,"chaos":40,"lowConfidence":true,"ratio":1},{"name":"The Hidden","divine":0.27,"chaos":40,"lowConfidence":true,"ratio":1},{"name":"The Feared","divine":0.2,"chaos":30,"lowConfidence":true,"ratio":1}]}