{"timestamp":1673514132974,"data":[{"name":"Factory","divine":1.63,"chaos":375,"lowConfidence":true},{"name":"Vaal Temple","divine":0.07,"chaos":18,"lowConfidence":false},{"name":"Vaal Pyramid","divine":0.04,"chaos":10,"lowConfidence":true},{"name":"Colonnade","divine":0.02,"chaos":6,"lowConfidence":true},{"name":"Ashen Wood","divine":0.02,"chaos":5,"lowConfidence":true},{"name":"Atoll","divine":0.02,"chaos":5,"lowConfidence":false},{"name":"Bog","divine":0.02,"chaos":5,"lowConfidence":true},{"name":"City Square","divine":0.02,"chaos":5,"lowConfidence":false},{"name":"Forking River","divine":0.02,"chaos":5,"lowConfidence":true},{"name":"Haunted Mansion","divine":0.02,"chaos":5,"lowConfidence":true},{"name":"Mesa","divine":0.02,"chaos":5,"lowConfidence":false},{"name":"Spider Forest","divine":0.02,"chaos":5,"lowConfidence":true},{"name":"Burial Chambers","divine":0.02,"chaos":4,"lowConfidence":false},{"name":"Canyon","divine":0.02,"chaos":4,"lowConfidence":true},{"name":"Cold River","divine":0.02,"chaos":4,"lowConfidence":true},{"name":"Courthouse","divine":0.02,"chaos":4,"lowConfidence":true},{"name":"Coves","divine":0.02,"chaos":4,"lowConfidence":false},{"name":"Crimson Temple","divine":0.02,"chaos":4,"lowConfidence":false},{"name":"Crimson Township","divine":0.02,"chaos":4,"lowConfidence":true},{"name":"Dark Forest","divine":0.02,"chaos":4,"lowConfidence":true},{"name":"Defiled Cathedral","divine":0.02,"chaos":4,"lowConfidence":false},{"name":"Dry Sea","divine":0.02,"chaos":4,"lowConfidence":true},{"name":"Dunes","divine":0.02,"chaos":4,"lowConfidence":false},{"name":"Grotto","divine":0.02,"chaos":4,"lowConfidence":true},{"name":"Mausoleum","divine":0.02,"chaos":4,"lowConfidence":false},{"name":"Maze","divine":0.02,"chaos":4,"lowConfidence":true},{"name":"Promenade","divine":0.02,"chaos":4,"lowConfidence":true},{"name":"Shore","divine":0.02,"chaos":4,"lowConfidence":true},{"name":"Strand","divine":0.02,"chaos":4,"lowConfidence":false},{"name":"Sunken City","divine":0.02,"chaos":4,"lowConfidence":true},{"name":"Temple","divine":0.02,"chaos":4,"lowConfidence":true},{"name":"Tower","divine":0.02,"chaos":4,"lowConfidence":true},{"name":"Toxic Sewer","divine":0.02,"chaos":4,"lowConfidence":false},{"name":"Underground River","divine":0.02,"chaos":4,"lowConfidence":true},{"name":"Acid Caverns","divine":0.01,"chaos":3,"lowConfidence":true},{"name":"Alleyways","divine":0.01,"chaos":3,"lowConfidence":true},{"name":"Beach","divine":0.02,"chaos":3,"lowConfidence":true},{"name":"Cemetery","divine":0.01,"chaos":3,"lowConfidence":true},{"name":"Crater","divine":0.01,"chaos":3,"lowConfidence":true},{"name":"Cursed Crypt","divine":0.01,"chaos":3,"lowConfidence":true},{"name":"Forbidden Woods","divine":0.01,"chaos":3,"lowConfidence":true},{"name":"Graveyard","divine":0.01,"chaos":3,"lowConfidence":true},{"name":"Overgrown Ruin","divine":0.01,"chaos":3,"lowConfidence":true},{"name":"Plateau","divine":0.01,"chaos":3,"lowConfidence":true},{"name":"Villa","divine":0.01,"chaos":3,"lowConfidence":true},{"name":"Ancient City","divine":0.01,"chaos":2,"lowConfidence":true},{"name":"Carcass","divine":0.01,"chaos":2,"lowConfidence":false},{"name":"Channel","divine":0.01,"chaos":2,"lowConfidence":true},{"name":"Foundry","divine":0.01,"chaos":2,"lowConfidence":true},{"name":"Ghetto","divine":0.01,"chaos":2,"lowConfidence":true},{"name":"Lair","divine":0.01,"chaos":2,"lowConfidence":true},{"name":"Museum","divine":0.01,"chaos":2,"lowConfidence":true},{"name":"Necropolis","divine":0.01,"chaos":2,"lowConfidence":true},{"name":"Phantasmagoria","divine":0.01,"chaos":2,"lowConfidence":true},{"name":"Pier","divine":0.01,"chaos":2,"lowConfidence":true},{"name":"Underground Sea","divine":0.01,"chaos":2,"lowConfidence":true},{"name":"Conqueror Maps","divine":0.11,"chaos":28,"lowConfidence":false},{"name":"Beachhead Maps","divine":0.08,"chaos":19,"lowConfidence":true},{"name":"Elder Maps","divine":0.06,"chaos":15,"lowConfidence":false},{"name":"Shaper Maps","divine":0.06,"chaos":15,"lowConfidence":false},{"name":"Blighted Maps","divine":0.04,"chaos":10,"lowConfidence":false}]}