{"timestamp":1671408071757,"data":[{"name":"Primeval","divine":0.5,"chaos":100,"lowConfidence":true},{"name":"Unearthed","divine":0.15,"chaos":30,"lowConfidence":false},{"name":"Sunken","divine":0.13,"chaos":25,"lowConfidence":true},{"name":"Glacial","divine":0.11,"chaos":22,"lowConfidence":true},{"name":"Enlightened","divine":0.1,"chaos":20,"lowConfidence":true},{"name":"Haunted","divine":0.1,"chaos":20,"lowConfidence":true},{"name":"Immaculate","divine":0.1,"chaos":20,"lowConfidence":true},{"name":"Nocturnal","divine":0.1,"chaos":20,"lowConfidence":true},{"name":"Sanguine","divine":0.09,"chaos":18,"lowConfidence":false},{"name":"Divided","divine":0.08,"chaos":15,"lowConfidence":false},{"name":"Backstreet","divine":0.05,"chaos":10,"lowConfidence":true},{"name":"Coastal","divine":0.05,"chaos":10,"lowConfidence":true},{"name":"Overgrown","divine":0.05,"chaos":10,"lowConfidence":true},{"name":"Battle-scarred","divine":0.05,"chaos":9,"lowConfidence":true},{"name":"Arboreal","divine":0.03,"chaos":5,"lowConfidence":true}]}