{"timestamp":1727079013532,"data":[{"name":"Haunted","divine":10,"chaos":1370,"lowConfidence":true,"ratio":1},{"name":"Sanguine","divine":10,"chaos":1330,"lowConfidence":true,"ratio":1},{"name":"Enlightened","divine":1.5,"chaos":206,"lowConfidence":true,"ratio":1},{"name":"Divided","divine":1,"chaos":137,"lowConfidence":true,"ratio":1},{"name":"Unearthed","divine":1,"chaos":133,"lowConfidence":true,"ratio":1},{"name":"Battle-scarred","divine":1,"chaos":132,"lowConfidence":true,"ratio":1},{"name":"Arboreal","divine":0.07,"chaos":10,"lowConfidence":true,"ratio":1}]}