{"timestamp":1673568073156,"data":[{"name":"Primeval","divine":3.5,"chaos":861,"lowConfidence":true},{"name":"Nocturnal","divine":1.5,"chaos":369,"lowConfidence":true},{"name":"Arboreal","divine":0.7,"chaos":172,"lowConfidence":true},{"name":"Immaculate","divine":0.6,"chaos":150,"lowConfidence":true},{"name":"Backstreet","divine":0.24,"chaos":60,"lowConfidence":true},{"name":"Battle-scarred","divine":0.2,"chaos":50,"lowConfidence":true},{"name":"Enlightened","divine":0.2,"chaos":50,"lowConfidence":true},{"name":"Glacial","divine":0.2,"chaos":50,"lowConfidence":true},{"name":"Sanguine","divine":0.2,"chaos":50,"lowConfidence":false},{"name":"Haunted","divine":0.18,"chaos":45,"lowConfidence":true},{"name":"Unearthed","divine":0.16,"chaos":40,"lowConfidence":true},{"name":"Divided","divine":0.14,"chaos":35,"lowConfidence":true},{"name":"Coastal","divine":0.08,"chaos":20,"lowConfidence":true},{"name":"Sunken","divine":0.08,"chaos":20,"lowConfidence":true}]}