{"timestamp":1711131020331,"data":[{"name":"T4 Aisling","divine":10,"chaos":1520,"lowConfidence":false,"ratio":1},{"name":"T4 Hillock Weapon 30%","divine":4,"chaos":604,"lowConfidence":true,"ratio":1},{"name":"T4 Hillock Armour 30%","divine":3,"chaos":474,"lowConfidence":true,"ratio":1},{"name":"T4 Hillock Flask 28%","divine":3,"chaos":465,"lowConfidence":true,"ratio":1},{"name":"T4/T3 Jorgin Tier 3 Talisman","divine":2,"chaos":300,"lowConfidence":true,"ratio":1},{"name":"T4 Vorici 1-6 White","divine":0.65,"chaos":100,"lowConfidence":false,"ratio":1}]}