{"timestamp":1692605419483,"data":[{"name":"T4 Hillock Weapon 30%","divine":0.41,"chaos":50,"lowConfidence":false,"ratio":1},{"name":"T4 Aisling","divine":0.35,"chaos":40,"lowConfidence":false,"ratio":1},{"name":"T4 Hillock Armour 30%","divine":0.38,"chaos":40,"lowConfidence":false,"ratio":1},{"name":"T4 Hillock Flask 28%","divine":0.29,"chaos":30,"lowConfidence":false,"ratio":1},{"name":"T4 Vorici 1-6 White","divine":0.21,"chaos":25,"lowConfidence":false,"ratio":1},{"name":"T4/T3 Jorgin Tier 3 Talisman","divine":0.14,"chaos":20,"lowConfidence":true,"ratio":1},{"name":"T3/T2/T1 Vorici White","divine":0.14,"chaos":15,"lowConfidence":false,"ratio":1},{"name":"T4/T3 Tora 200m Gem XP","divine":0.1,"chaos":10,"lowConfidence":false,"ratio":1},{"name":"Locus of Corruption (Item)","divine":0.54,"chaos":66,"lowConfidence":true,"ratio":1},{"name":"Doryani Institute (Gem)","divine":0.39,"chaos":60,"lowConfidence":true,"ratio":1}]}